kanasplit/__init__.py
kanasplit/tokenizer.py
kanasplit-1.0.2.dist-info/METADATA
kanasplit-1.0.2.dist-info/WHEEL
kanasplit-1.0.2.dist-info/entry_points.txt
kanasplit-1.0.2.dist-info/top_level.txt
kanasplit-1.0.2.dist-info/RECORD
