Metadata-Version: 2.2
Name: kanasplit
Version: 1.0.2
Summary: A Japanese text tokenizer with POS tagging and Jisho.org integration.
Home-page: https://github.com/byteMe394/KanaSplit
Author: José Trujillo
Author-email: joseantonio_tf@outlook.com
Project-URL: Documentation, https://github.com/byteMe394/KanaSplit#readme
Project-URL: Source, https://github.com/byteMe394/KanaSplit
Project-URL: Issue Tracker, https://github.com/byteMe394/KanaSplit/issues
Keywords: Japanese NLP tokenizer MeCab Jisho
Classifier: Programming Language :: Python :: 3
Classifier: License :: OSI Approved :: MIT License
Classifier: Operating System :: OS Independent
Classifier: Natural Language :: Japanese
Classifier: Topic :: Text Processing :: Linguistic
Classifier: Intended Audience :: Developers
Classifier: Intended Audience :: Education
Requires-Python: >=3.6
Requires-Dist: ratelimit<3.0,>=2.2
Requires-Dist: requests>=2.31.0
Requires-Dist: mecab-python3
Dynamic: author
Dynamic: author-email
Dynamic: classifier
Dynamic: description
Dynamic: description-content-type
Dynamic: home-page
Dynamic: keywords
Dynamic: project-url
Dynamic: requires-dist
Dynamic: requires-python
Dynamic: summary
